tfrunner/__init__.py
tfrunner/exceptions.py
tfrunner/main.py
tfrunner/utils.py
tfrunner/automations/__init__.py
tfrunner/commands/__init__.py
tfrunner/commands/apply.py
tfrunner/commands/destroy.py
tfrunner/commands/fmt.py
tfrunner/commands/init.py
tfrunner/commands/output.py
tfrunner/commands/plan.py
tfrunner/commands/validate.py
tfrunner/env/__init__.py
tfrunner/env/env_export.py
tfrunner/env/tfvars_env_loader.py
tfrunner/projects/__init__.py
tfrunner/projects/base.py
tfrunner/secrets_backend/__init__.py
tfrunner/secrets_backend/base.py
tfrunner/secrets_backend/doppler.py
tfrunner/secrets_backend/factory.py
tfrunner/secrets_backend/gitlab.py
tfrunner/state_backend/__init__.py
tfrunner/state_backend/base.py
tfrunner/state_backend/factory.py
tfrunner/state_backend/generic.py
tfrunner/state_backend/gitlab.py
tfrunner-0.12.5.dist-info/METADATA
tfrunner-0.12.5.dist-info/WHEEL
tfrunner-0.12.5.dist-info/entry_points.txt
tfrunner-0.12.5.dist-info/top_level.txt
tfrunner-0.12.5.dist-info/RECORD
