Metadata-Version: 2.4
Name: tfrunner
Version: 0.12.5
Summary: A cli tool used to make running terraform or opentofu project simpler. Includes secret fetching and remote state management.
Requires-Python: >=3.13
Requires-Dist: doppler-sdk>=1.3.0
Requires-Dist: pydantic>=2.10.6
Requires-Dist: pyyaml>=6.0.2
Requires-Dist: requests>=2.32.3
Requires-Dist: toml>=0.10.2
Requires-Dist: typer>=0.15.1
